UQpyDTO.py
quofemDTOs.py
distributions/UniformDTOs.py
modules/ModuleDTOs.py
reliability/ReliabilityMethodsDTOs.py
runmodel/RunModelDTOs.py
sampling/mcmc/StretchDto.py
UQpyDTOs-0.1.56.dist-info/LICENCE.txt
UQpyDTOs-0.1.56.dist-info/METADATA
UQpyDTOs-0.1.56.dist-info/WHEEL
UQpyDTOs-0.1.56.dist-info/top_level.txt
UQpyDTOs-0.1.56.dist-info/RECORD
