Metadata-Version: 2.1
Name: UQpyDTOs
Version: 0.1.56
Summary: A collection of DTOs to deserialize json into UQpy classes
Home-page: https://github.com/DTsapetis/UQpyDTOs
Author: Dimitris Tsapetis
License: MIT
Platform: OSX
Platform: Windows
Platform: Linux
Classifier: Programming Language :: Python :: 3
Classifier: License :: OSI Approved :: MIT License
Classifier: Natural Language :: English
License-File: LICENCE.txt
Requires-Dist: UQpy
